Metadata-Version: 2.4
Name: fedops
Version: 1.1.30.4
Summary: FL Lifecycle Operations Management Platform
Home-page: https://github.com/gachon-CCLab/FedOps.git
Author: Semo Yang
Author-email: tpah20@gmail.com
Classifier: Development Status :: 5 - Production/Stable
Classifier: License :: OSI Approved :: MIT License
Classifier: Programming Language :: Python :: 3
Classifier: Programming Language :: Python :: 3.7
Classifier: Programming Language :: Python :: 3.8
Classifier: Programming Language :: Python :: 3.9
Classifier: Programming Language :: Python :: 3.10
Classifier: Programming Language :: Python :: 3.11
Requires-Dist: flwr>=1.0.0
Requires-Dist: flwr[simulation]
Requires-Dist: fastapi>=0.70.1
Requires-Dist: uvicorn[standard]>=0.16.0
Requires-Dist: requests>=2.26.0
Requires-Dist: pydantic>=1.10.7
Requires-Dist: numpy==1.26.4
Requires-Dist: wandb>=0.15.0
Requires-Dist: pandas>=1.5.3
Requires-Dist: pyyaml>=5.0
Requires-Dist: boto3>=1.24.0
Requires-Dist: hydra-core
Requires-Dist: numba
Requires-Dist: tqdm
Requires-Dist: transformers==4.43.1
Requires-Dist: trl==0.8.1
Requires-Dist: scikit-learn
Requires-Dist: bitsandbytes
Requires-Dist: peft==0.14.0
Requires-Dist: grad-cam
Requires-Dist: optuna>=3.6
Dynamic: author
Dynamic: author-email
Dynamic: classifier
Dynamic: description
Dynamic: description-content-type
Dynamic: home-page
Dynamic: requires-dist
Dynamic: summary
